<chunk name="Object" index="0">
  <items count="2">
    <item name="GUID" type_name="gh_guid" type_code="9">2fcc2743-8339-4cdf-a046-a1f17439191d</item>
    <item name="Name" type_name="gh_string" type_code="10">Remap Numbers</item>
  </items>
  <chunks count="1">
    <chunk name="Container">
      <items count="5">
        <item name="Description" type_name="gh_string" type_code="10">Remap numbers into a new numeric domain</item>
        <item name="Hidden" type_name="gh_bool" type_code="1">true</item>
        <item name="InstanceGuid" type_name="gh_guid" type_code="9">4defbc80-a84c-4c89-8f14-bf52daaf78ca</item>
        <item name="Name" type_name="gh_string" type_code="10">Remap Numbers</item>
        <item name="NickName" type_name="gh_string" type_code="10">ReMap</item>
      </items>
      <chunks count="6">
        <chunk name="Attributes">
          <items count="2">
            <item name="Bounds" type_name="gh_drawing_rectanglef" type_code="35">
              <X>12699</X>
              <Y>1131</Y>
              <W>65</W>
              <H>64</H>
            </item>
            <item name="Pivot" type_name="gh_drawing_pointf" type_code="31">
              <X>12730</X>
              <Y>1163</Y>
            </item>
          </items>
        </chunk>
        <chunk name="param_input" index="0">
          <items count="7">
            <item name="Description" type_name="gh_string" type_code="10">Value to remap</item>
            <item name="InstanceGuid" type_name="gh_guid" type_code="9">767aebb0-ac12-4146-bdbe-5f1a1a488363</item>
            <item name="Name" type_name="gh_string" type_code="10">Value</item>
            <item name="NickName" type_name="gh_string" type_code="10">V</item>
            <item name="Optional" type_name="gh_bool" type_code="1">false</item>
            <item name="Source" index="0" type_name="gh_guid" type_code="9">fd0371d0-9559-46a5-ba17-28f08f8c1bf2</item>
            <item name="SourceCount" type_name="gh_int32" type_code="3">1</item>
          </items>
          <chunks count="1">
            <chunk name="Attributes">
              <items count="2">
                <item name="Bounds" type_name="gh_drawing_rectanglef" type_code="35">
                  <X>12701</X>
                  <Y>1133</Y>
                  <W>14</W>
                  <H>20</H>
                </item>
                <item name="Pivot" type_name="gh_drawing_pointf" type_code="31">
                  <X>12709.5</X>
                  <Y>1143</Y>
                </item>
              </items>
            </chunk>
          </chunks>
        </chunk>
        <chunk name="param_input" index="1">
          <items count="7">
            <item name="Description" type_name="gh_string" type_code="10">Source domain</item>
            <item name="InstanceGuid" type_name="gh_guid" type_code="9">5db23c81-4d57-4e19-84d8-115d2a5de239</item>
            <item name="Name" type_name="gh_string" type_code="10">Source</item>
            <item name="NickName" type_name="gh_string" type_code="10">S</item>
            <item name="Optional" type_name="gh_bool" type_code="1">false</item>
            <item name="Source" index="0" type_name="gh_guid" type_code="9">6e2ab6f0-301a-4bd8-8d5d-fb9daabaec33</item>
            <item name="SourceCount" type_name="gh_int32" type_code="3">1</item>
          </items>
          <chunks count="2">
            <chunk name="Attributes">
              <items count="2">
                <item name="Bounds" type_name="gh_drawing_rectanglef" type_code="35">
                  <X>12701</X>
                  <Y>1153</Y>
                  <W>14</W>
                  <H>20</H>
                </item>
                <item name="Pivot" type_name="gh_drawing_pointf" type_code="31">
                  <X>12709.5</X>
                  <Y>1163</Y>
                </item>
              </items>
            </chunk>
            <chunk name="PersistentData">
              <items count="1">
                <item name="Count" type_name="gh_int32" type_code="3">1</item>
              </items>
              <chunks count="1">
                <chunk name="Branch" index="0">
                  <items count="2">
                    <item name="Count" type_name="gh_int32" type_code="3">1</item>
                    <item name="Path" type_name="gh_string" type_code="10">{0}</item>
                  </items>
                  <chunks count="1">
                    <chunk name="Item" index="0">
                      <items count="1">
                        <item name="Interval" type_name="gh_interval1d" type_code="60">
                          <A>0</A>
                          <B>1</B>
                        </item>
                      </items>
                    </chunk>
                  </chunks>
                </chunk>
              </chunks>
            </chunk>
          </chunks>
        </chunk>
        <chunk name="param_input" index="2">
          <items count="7">
            <item name="Description" type_name="gh_string" type_code="10">Target domain</item>
            <item name="InstanceGuid" type_name="gh_guid" type_code="9">cac9bc83-9fb1-4e8f-bc80-e40f400b42e7</item>
            <item name="Name" type_name="gh_string" type_code="10">Target</item>
            <item name="NickName" type_name="gh_string" type_code="10">T</item>
            <item name="Optional" type_name="gh_bool" type_code="1">false</item>
            <item name="Source" index="0" type_name="gh_guid" type_code="9">5ebdfeec-9630-45b0-a2e5-50446cd3cdd6</item>
            <item name="SourceCount" type_name="gh_int32" type_code="3">1</item>
          </items>
          <chunks count="2">
            <chunk name="Attributes">
              <items count="2">
                <item name="Bounds" type_name="gh_drawing_rectanglef" type_code="35">
                  <X>12701</X>
                  <Y>1173</Y>
                  <W>14</W>
                  <H>20</H>
                </item>
                <item name="Pivot" type_name="gh_drawing_pointf" type_code="31">
                  <X>12709.5</X>
                  <Y>1183</Y>
                </item>
              </items>
            </chunk>
            <chunk name="PersistentData">
              <items count="1">
                <item name="Count" type_name="gh_int32" type_code="3">1</item>
              </items>
              <chunks count="1">
                <chunk name="Branch" index="0">
                  <items count="2">
                    <item name="Count" type_name="gh_int32" type_code="3">1</item>
                    <item name="Path" type_name="gh_string" type_code="10">{0}</item>
                  </items>
                  <chunks count="1">
                    <chunk name="Item" index="0">
                      <items count="1">
                        <item name="Interval" type_name="gh_interval1d" type_code="60">
                          <A>0</A>
                          <B>1</B>
                        </item>
                      </items>
                    </chunk>
                  </chunks>
                </chunk>
              </chunks>
            </chunk>
          </chunks>
        </chunk>
        <chunk name="param_output" index="0">
          <items count="6">
            <item name="Description" type_name="gh_string" type_code="10">Remapped number</item>
            <item name="InstanceGuid" type_name="gh_guid" type_code="9">0da810ea-43d4-40a7-8ad6-2d6cb17c841b</item>
            <item name="Name" type_name="gh_string" type_code="10">Mapped</item>
            <item name="NickName" type_name="gh_string" type_code="10">R</item>
            <item name="Optional" type_name="gh_bool" type_code="1">false</item>
            <item name="SourceCount" type_name="gh_int32" type_code="3">0</item>
          </items>
          <chunks count="1">
            <chunk name="Attributes">
              <items count="2">
                <item name="Bounds" type_name="gh_drawing_rectanglef" type_code="35">
                  <X>12745</X>
                  <Y>1133</Y>
                  <W>17</W>
                  <H>30</H>
                </item>
                <item name="Pivot" type_name="gh_drawing_pointf" type_code="31">
                  <X>12753.5</X>
                  <Y>1148</Y>
                </item>
              </items>
            </chunk>
          </chunks>
        </chunk>
        <chunk name="param_output" index="1">
          <items count="6">
            <item name="Description" type_name="gh_string" type_code="10">Remapped and clipped number</item>
            <item name="InstanceGuid" type_name="gh_guid" type_code="9">d6e6f3fe-eb6c-4a1a-8a95-ce409b2f0476</item>
            <item name="Name" type_name="gh_string" type_code="10">Clipped</item>
            <item name="NickName" type_name="gh_string" type_code="10">C</item>
            <item name="Optional" type_name="gh_bool" type_code="1">false</item>
            <item name="SourceCount" type_name="gh_int32" type_code="3">0</item>
          </items>
          <chunks count="1">
            <chunk name="Attributes">
              <items count="2">
                <item name="Bounds" type_name="gh_drawing_rectanglef" type_code="35">
                  <X>12745</X>
                  <Y>1163</Y>
                  <W>17</W>
                  <H>30</H>
                </item>
                <item name="Pivot" type_name="gh_drawing_pointf" type_code="31">
                  <X>12753.5</X>
                  <Y>1178</Y>
                </item>
              </items>
            </chunk>
          </chunks>
        </chunk>
      </chunks>
    </chunk>
  </chunks>
</chunk>