<chunk name="Object" index="0">
  <items count="3">
    <item name="GUID" type_name="gh_guid" type_code="9">539e880d-cfd1-4ac0-b1a4-a249558d076a</item>
    <item name="Lib" type_name="gh_guid" type_code="9">d45b0aa7-fa27-4b91-3a40-b9f60d192781</item>
    <item name="Name" type_name="gh_string" type_code="10">Nos Simulation V.4</item>
  </items>
  <chunks count="1">
    <chunk name="Container">
      <items count="14">
        <item name="Description" type_name="gh_string" type_code="10">Generates the final KUKA commands and performs the simulation</item>
        <item name="Hidden" type_name="gh_bool" type_code="1">true</item>
        <item name="IconDisplay" type_name="gh_int32" type_code="3">1</item>
        <item name="InstanceGuid" type_name="gh_guid" type_code="9">e2b89de9-d83f-41e5-ad1d-21dbd0e509d3</item>
        <item name="Name" type_name="gh_string" type_code="10">Nos Simulation V.4</item>
        <item name="NickName" type_name="gh_string" type_code="10">NOS.S.V4</item>
        <item name="OptimzieBTN" type_name="gh_int32" type_code="3">0</item>
        <item name="Show_Original_Meshes" type_name="gh_bool" type_code="1">false</item>
        <item name="Simulation" type_name="gh_double" type_code="6">0</item>
        <item name="SimulationControls.nextcollision" type_name="gh_int32" type_code="3">0</item>
        <item name="SimulationControls.play" type_name="gh_int32" type_code="3">0</item>
        <item name="SimulationControls.previousCollsion" type_name="gh_int32" type_code="3">0</item>
        <item name="SimulationControls.slownDN" type_name="gh_int32" type_code="3">0</item>
        <item name="SimulationControls.speedUP" type_name="gh_int32" type_code="3">0</item>
      </items>
      <chunks count="12">
        <chunk name="Attributes">
          <items count="2">
            <item name="Bounds" type_name="gh_drawing_rectanglef" type_code="35">
              <X>21775</X>
              <Y>10306</Y>
              <W>196</W>
              <H>288</H>
            </item>
            <item name="Pivot" type_name="gh_drawing_pointf" type_code="31">
              <X>21844</X>
              <Y>10400</Y>
            </item>
          </items>
        </chunk>
        <chunk name="param_input" index="0">
          <items count="9">
            <item name="Description" type_name="gh_string" type_code="10">Printing robot</item>
            <item name="Hidden" type_name="gh_bool" type_code="1">true</item>
            <item name="InstanceGuid" type_name="gh_guid" type_code="9">16da279c-dda0-4f05-a094-27a8843d536f</item>
            <item name="Name" type_name="gh_string" type_code="10">Primary</item>
            <item name="NickName" type_name="gh_string" type_code="10">P.R.</item>
            <item name="Optional" type_name="gh_bool" type_code="1">true</item>
            <item name="Source" index="0" type_name="gh_guid" type_code="9">0f7a226a-770c-4b16-9cda-fc9926d72df6</item>
            <item name="SourceCount" type_name="gh_int32" type_code="3">1</item>
            <item name="WireDisplay" type_name="gh_int32" type_code="3">2</item>
          </items>
          <chunks count="1">
            <chunk name="Attributes">
              <items count="2">
                <item name="Bounds" type_name="gh_drawing_rectanglef" type_code="35">
                  <X>21779</X>
                  <Y>10310</Y>
                  <W>50</W>
                  <H>20</H>
                </item>
                <item name="Pivot" type_name="gh_drawing_pointf" type_code="31">
                  <X>21805.5</X>
                  <Y>10320</Y>
                </item>
              </items>
            </chunk>
          </chunks>
        </chunk>
        <chunk name="param_input" index="1">
          <items count="9">
            <item name="Description" type_name="gh_string" type_code="10">Smoothing/Positioning/Marking robot</item>
            <item name="Hidden" type_name="gh_bool" type_code="1">true</item>
            <item name="InstanceGuid" type_name="gh_guid" type_code="9">596643a7-a4ed-45d0-8f2f-ba97022b319b</item>
            <item name="Name" type_name="gh_string" type_code="10">Secondary</item>
            <item name="NickName" type_name="gh_string" type_code="10">S.R.</item>
            <item name="Optional" type_name="gh_bool" type_code="1">true</item>
            <item name="Source" index="0" type_name="gh_guid" type_code="9">25c48f5e-06c2-43ef-96c7-67f4721ad7c3</item>
            <item name="SourceCount" type_name="gh_int32" type_code="3">1</item>
            <item name="WireDisplay" type_name="gh_int32" type_code="3">2</item>
          </items>
          <chunks count="1">
            <chunk name="Attributes">
              <items count="2">
                <item name="Bounds" type_name="gh_drawing_rectanglef" type_code="35">
                  <X>21779</X>
                  <Y>10330</Y>
                  <W>50</W>
                  <H>20</H>
                </item>
                <item name="Pivot" type_name="gh_drawing_pointf" type_code="31">
                  <X>21805.5</X>
                  <Y>10340</Y>
                </item>
              </items>
            </chunk>
          </chunks>
        </chunk>
        <chunk name="param_input" index="2">
          <items count="12">
            <item name="Description" type_name="gh_string" type_code="10">Contains commands that moves and controls the end effector of the robot.</item>
            <item name="Hidden" type_name="gh_bool" type_code="1">true</item>
            <item name="InstanceGuid" type_name="gh_guid" type_code="9">b12963fb-8a38-45e2-a5fe-200c58bdcef1</item>
            <item name="Name" type_name="gh_string" type_code="10">Tool path</item>
            <item name="NickName" type_name="gh_string" type_code="10">ToolPath</item>
            <item name="Optional" type_name="gh_bool" type_code="1">false</item>
            <item name="Source" index="0" type_name="gh_guid" type_code="9">593ccc4b-7f92-47e0-ae88-d57fef34e8cc</item>
            <item name="SourceCount" type_name="gh_int32" type_code="3">1</item>
            <item name="colorByVelocity" type_name="gh_bool" type_code="1">false</item>
            <item name="isInternalized" type_name="gh_bool" type_code="1">false</item>
            <item name="showSpeed" type_name="gh_bool" type_code="1">false</item>
            <item name="showStrips" type_name="gh_bool" type_code="1">false</item>
          </items>
          <chunks count="1">
            <chunk name="Attributes">
              <items count="2">
                <item name="Bounds" type_name="gh_drawing_rectanglef" type_code="35">
                  <X>21779</X>
                  <Y>10350</Y>
                  <W>50</W>
                  <H>20</H>
                </item>
                <item name="Pivot" type_name="gh_drawing_pointf" type_code="31">
                  <X>21805.5</X>
                  <Y>10360</Y>
                </item>
              </items>
            </chunk>
          </chunks>
        </chunk>
        <chunk name="param_input" index="3">
          <items count="10">
            <item name="Access" type_name="gh_int32" type_code="3">1</item>
            <item name="Description" type_name="gh_string" type_code="10">Rigid body for collision</item>
            <item name="Hidden" type_name="gh_bool" type_code="1">true</item>
            <item name="InstanceGuid" type_name="gh_guid" type_code="9">f6f04468-6ce1-4064-8dcf-eb3a632305ae</item>
            <item name="Name" type_name="gh_string" type_code="10">Body</item>
            <item name="NickName" type_name="gh_string" type_code="10">Body</item>
            <item name="Optional" type_name="gh_bool" type_code="1">true</item>
            <item name="Source" index="0" type_name="gh_guid" type_code="9">cf67d022-e6e3-4431-8c23-0af1ddc73380</item>
            <item name="SourceCount" type_name="gh_int32" type_code="3">1</item>
            <item name="WireDisplay" type_name="gh_int32" type_code="3">2</item>
          </items>
          <chunks count="1">
            <chunk name="Attributes">
              <items count="2">
                <item name="Bounds" type_name="gh_drawing_rectanglef" type_code="35">
                  <X>21779</X>
                  <Y>10370</Y>
                  <W>50</W>
                  <H>20</H>
                </item>
                <item name="Pivot" type_name="gh_drawing_pointf" type_code="31">
                  <X>21805.5</X>
                  <Y>10380</Y>
                </item>
              </items>
            </chunk>
          </chunks>
        </chunk>
        <chunk name="param_input" index="4">
          <items count="6">
            <item name="Description" type_name="gh_string" type_code="10">Run optimization in background</item>
            <item name="InstanceGuid" type_name="gh_guid" type_code="9">04fc6e64-02b1-4a84-99f9-53ab8c6eb20e</item>
            <item name="Name" type_name="gh_string" type_code="10">Background_Process</item>
            <item name="NickName" type_name="gh_string" type_code="10">B.P.</item>
            <item name="Optional" type_name="gh_bool" type_code="1">false</item>
            <item name="SourceCount" type_name="gh_int32" type_code="3">0</item>
          </items>
          <chunks count="2">
            <chunk name="Attributes">
              <items count="2">
                <item name="Bounds" type_name="gh_drawing_rectanglef" type_code="35">
                  <X>21779</X>
                  <Y>10390</Y>
                  <W>50</W>
                  <H>20</H>
                </item>
                <item name="Pivot" type_name="gh_drawing_pointf" type_code="31">
                  <X>21805.5</X>
                  <Y>10400</Y>
                </item>
              </items>
            </chunk>
            <chunk name="PersistentData">
              <items count="1">
                <item name="Count" type_name="gh_int32" type_code="3">1</item>
              </items>
              <chunks count="1">
                <chunk name="Branch" index="0">
                  <items count="2">
                    <item name="Count" type_name="gh_int32" type_code="3">1</item>
                    <item name="Path" type_name="gh_string" type_code="10">{0}</item>
                  </items>
                  <chunks count="1">
                    <chunk name="Item" index="0">
                      <items count="1">
                        <item name="boolean" type_name="gh_bool" type_code="1">true</item>
                      </items>
                    </chunk>
                  </chunks>
                </chunk>
              </chunks>
            </chunk>
          </chunks>
        </chunk>
        <chunk name="param_input" index="5">
          <items count="8">
            <item name="Description" type_name="gh_string" type_code="10">Contains a frame for KUKA|prc</item>
            <item name="InstanceGuid" type_name="gh_guid" type_code="9">c9e84053-60f9-4df4-9750-16698531688e</item>
            <item name="Name" type_name="gh_string" type_code="10">Base1</item>
            <item name="NickName" type_name="gh_string" type_code="10">B1.</item>
            <item name="Optional" type_name="gh_bool" type_code="1">true</item>
            <item name="Source" index="0" type_name="gh_guid" type_code="9">c73c78e5-3c46-492f-b8fd-d21d6112d869</item>
            <item name="SourceCount" type_name="gh_int32" type_code="3">1</item>
            <item name="WireDisplay" type_name="gh_int32" type_code="3">2</item>
          </items>
          <chunks count="1">
            <chunk name="Attributes">
              <items count="2">
                <item name="Bounds" type_name="gh_drawing_rectanglef" type_code="35">
                  <X>21779</X>
                  <Y>10410</Y>
                  <W>50</W>
                  <H>20</H>
                </item>
                <item name="Pivot" type_name="gh_drawing_pointf" type_code="31">
                  <X>21805.5</X>
                  <Y>10420</Y>
                </item>
              </items>
            </chunk>
          </chunks>
        </chunk>
        <chunk name="param_input" index="6">
          <items count="8">
            <item name="Description" type_name="gh_string" type_code="10">Contains a frame for KUKA|prc</item>
            <item name="InstanceGuid" type_name="gh_guid" type_code="9">2acb9c03-6b86-4e4f-a92a-9c0a2789821d</item>
            <item name="Name" type_name="gh_string" type_code="10">Base2</item>
            <item name="NickName" type_name="gh_string" type_code="10">B2.</item>
            <item name="Optional" type_name="gh_bool" type_code="1">true</item>
            <item name="Source" index="0" type_name="gh_guid" type_code="9">17fbffc2-085d-4131-a3b3-a4a3bd60957b</item>
            <item name="SourceCount" type_name="gh_int32" type_code="3">1</item>
            <item name="WireDisplay" type_name="gh_int32" type_code="3">2</item>
          </items>
          <chunks count="1">
            <chunk name="Attributes">
              <items count="2">
                <item name="Bounds" type_name="gh_drawing_rectanglef" type_code="35">
                  <X>21779</X>
                  <Y>10430</Y>
                  <W>50</W>
                  <H>20</H>
                </item>
                <item name="Pivot" type_name="gh_drawing_pointf" type_code="31">
                  <X>21805.5</X>
                  <Y>10440</Y>
                </item>
              </items>
            </chunk>
          </chunks>
        </chunk>
        <chunk name="param_input" index="7">
          <items count="6">
            <item name="Description" type_name="gh_string" type_code="10">Detects the collisions</item>
            <item name="InstanceGuid" type_name="gh_guid" type_code="9">8d25ccf7-bb43-447d-9549-b5f4b024bd99</item>
            <item name="Name" type_name="gh_string" type_code="10">Collision</item>
            <item name="NickName" type_name="gh_string" type_code="10">Col.</item>
            <item name="Optional" type_name="gh_bool" type_code="1">false</item>
            <item name="SourceCount" type_name="gh_int32" type_code="3">0</item>
          </items>
          <chunks count="2">
            <chunk name="Attributes">
              <items count="2">
                <item name="Bounds" type_name="gh_drawing_rectanglef" type_code="35">
                  <X>21779</X>
                  <Y>10450</Y>
                  <W>50</W>
                  <H>20</H>
                </item>
                <item name="Pivot" type_name="gh_drawing_pointf" type_code="31">
                  <X>21805.5</X>
                  <Y>10460</Y>
                </item>
              </items>
            </chunk>
            <chunk name="PersistentData">
              <items count="1">
                <item name="Count" type_name="gh_int32" type_code="3">1</item>
              </items>
              <chunks count="1">
                <chunk name="Branch" index="0">
                  <items count="2">
                    <item name="Count" type_name="gh_int32" type_code="3">1</item>
                    <item name="Path" type_name="gh_string" type_code="10">{0}</item>
                  </items>
                  <chunks count="1">
                    <chunk name="Item" index="0">
                      <items count="1">
                        <item name="boolean" type_name="gh_bool" type_code="1">false</item>
                      </items>
                    </chunk>
                  </chunks>
                </chunk>
              </chunks>
            </chunk>
          </chunks>
        </chunk>
        <chunk name="param_input" index="8">
          <items count="7">
            <item name="Description" type_name="gh_string" type_code="10">Set of parameters for solver to find the collision free path using the redandency</item>
            <item name="InstanceGuid" type_name="gh_guid" type_code="9">c7a5cef6-8dd4-4081-9c9b-98c5c1d3a139</item>
            <item name="Name" type_name="gh_string" type_code="10">Solver Params</item>
            <item name="NickName" type_name="gh_string" type_code="10">So.Ps.</item>
            <item name="Optional" type_name="gh_bool" type_code="1">true</item>
            <item name="Source" index="0" type_name="gh_guid" type_code="9">a7436ea6-510b-4822-87ab-550ef8a304bf</item>
            <item name="SourceCount" type_name="gh_int32" type_code="3">1</item>
          </items>
          <chunks count="1">
            <chunk name="Attributes">
              <items count="2">
                <item name="Bounds" type_name="gh_drawing_rectanglef" type_code="35">
                  <X>21779</X>
                  <Y>10470</Y>
                  <W>50</W>
                  <H>20</H>
                </item>
                <item name="Pivot" type_name="gh_drawing_pointf" type_code="31">
                  <X>21805.5</X>
                  <Y>10480</Y>
                </item>
              </items>
            </chunk>
          </chunks>
        </chunk>
        <chunk name="param_output" index="0">
          <items count="6">
            <item name="Description" type_name="gh_string" type_code="10">Contains a command for KUKA|prc</item>
            <item name="InstanceGuid" type_name="gh_guid" type_code="9">21c44c27-3120-49db-a5c9-06c9d1c56ac2</item>
            <item name="Name" type_name="gh_string" type_code="10">Robot1 Commands</item>
            <item name="NickName" type_name="gh_string" type_code="10">KUKA Command</item>
            <item name="Optional" type_name="gh_bool" type_code="1">false</item>
            <item name="SourceCount" type_name="gh_int32" type_code="3">0</item>
          </items>
          <chunks count="1">
            <chunk name="Attributes">
              <items count="2">
                <item name="Bounds" type_name="gh_drawing_rectanglef" type_code="35">
                  <X>21880</X>
                  <Y>10310</Y>
                  <W>91</W>
                  <H>90</H>
                </item>
                <item name="Pivot" type_name="gh_drawing_pointf" type_code="31">
                  <X>21904.5</X>
                  <Y>10355</Y>
                </item>
              </items>
            </chunk>
          </chunks>
        </chunk>
        <chunk name="param_output" index="1">
          <items count="6">
            <item name="Description" type_name="gh_string" type_code="10">Contains a command for KUKA|prc</item>
            <item name="InstanceGuid" type_name="gh_guid" type_code="9">a9ab9df7-2dd7-4b0b-bfc1-a4df03054a9e</item>
            <item name="Name" type_name="gh_string" type_code="10">Robot2 Commands</item>
            <item name="NickName" type_name="gh_string" type_code="10">KUKA Command</item>
            <item name="Optional" type_name="gh_bool" type_code="1">false</item>
            <item name="SourceCount" type_name="gh_int32" type_code="3">0</item>
          </items>
          <chunks count="1">
            <chunk name="Attributes">
              <items count="2">
                <item name="Bounds" type_name="gh_drawing_rectanglef" type_code="35">
                  <X>21880</X>
                  <Y>10400</Y>
                  <W>91</W>
                  <H>90</H>
                </item>
                <item name="Pivot" type_name="gh_drawing_pointf" type_code="31">
                  <X>21904.5</X>
                  <Y>10445</Y>
                </item>
              </items>
            </chunk>
          </chunks>
        </chunk>
      </chunks>
    </chunk>
  </chunks>
</chunk>